{
  "d": {
    "__metadata": {
      "id": "https://mydemo21.teamwork.net:44301/sap/opu/odata/SAP/Z_PURREQUISITION_EXT_SRV/PR_HeaderSet('0010000508')",
      "uri": "https://mydemo21.teamwork.net:44301/sap/opu/odata/SAP/Z_PURREQUISITION_EXT_SRV/PR_HeaderSet('0010000508')",
      "type": "Z_PURREQUISITION_EXT_SRV.PR_HeaderType"
    },
    "PurReqnDescription": "",
    "PreqNo": "0010000508",
    "PrType": "NB",
    "StatusID": "S",
    "TotalValue": "0.00",
    "AutoSource": "",
    "Memory": "",
    "HoldComplete": "",
    "HoldUncomplete": "",
    "MemoryType": "",
    "TestRun": "",
    "To_PRItems": {
      "results": [
        {
          "__metadata": {
            "id": "https://mydemo21.teamwork.net:44301/sap/opu/odata/SAP/Z_PURREQUISITION_EXT_SRV/PR_ItemSet(PreqNo='10000508',PreqItem='00010')",
            "uri": "https://mydemo21.teamwork.net:44301/sap/opu/odata/SAP/Z_PURREQUISITION_EXT_SRV/PR_ItemSet(PreqNo='10000508',PreqItem='00010')",
            "type": "Z_PURREQUISITION_EXT_SRV.PR_ItemType"
          },
          "CreationDate": "\/Date(1539907200000)\/",
          "LastChangeDate": "\/Date(1540339200000)\/",
          "PreqNo": "10000508",
          "PreqItem": "00010",
          "DeleteInd": "",
          "AcctAssCat": "",
          "Material": "NL001",
          "ItemDescription": "Screw",
          "Quantity": "1.000",
          "Unit": "PC",
          "PreqPrice": "0.000000000",
          "PriceUnit": "1",
          "Currency": "USD",
          "DelivDate": "\/Date(1539907200000)\/",
          "PurGroup": "Z90",
          "Plant": "1710",
          "PurchOrg": "1710",
          "FixedVend": "17300001",
          "StatusID": "B",
          "MatlGroup": "YBMM01",
          "PONumber": "4500000211",
          "POItem": "00010",
          "POSupplier": "",
          "POCreationDate": "\/Date(1540252800000)\/",
          "PR_Completed": false,
          "PO_Completed": false,
          "to_accounts": {
            "results": []
          },
          "to_GoodsReceiptSet": {
            "__deferred": {
              "uri": "https://mydemo21.teamwork.net:44301/sap/opu/odata/SAP/Z_PURREQUISITION_EXT_SRV/PR_ItemSet(PreqNo='10000508',PreqItem='00010')/to_GoodsReceiptSet"
            }
          },
          "to_invoices": {
            "__deferred": {
              "uri": "https://mydemo21.teamwork.net:44301/sap/opu/odata/SAP/Z_PURREQUISITION_EXT_SRV/PR_ItemSet(PreqNo='10000508',PreqItem='00010')/to_invoices"
            }
          }
        }
      ]
    }
  }
}
